myLib/__init__.py
myLib/datastructures/__init__.py
myLib/datastructures/linear/CDLL.py
myLib/datastructures/linear/CSLL.py
myLib/datastructures/linear/DLL.py
myLib/datastructures/linear/QueueLL.py
myLib/datastructures/linear/SLL.py
myLib/datastructures/linear/StackLL.py
myLib/datastructures/linear/__init__.py
myLib/datastructures/nodes/DNode.py
myLib/datastructures/nodes/TNode.py
myLib/datastructures/nodes/__init__.py
myLib/datastructures/trees/AVL.py
myLib/datastructures/trees/BST.py
myLib/datastructures/trees/__init__.py
test/BSTtest.py
test/CDLLtest.py
test/CSLLtest.py
test/DLLtest.py
test/QueueLLtest.py
test/SLLtest.py
test/StackLL.py
test/StackLLtest.py
test/__init__.py
test/avltest.py
test/test.py
python_library_30153653-1.5.0.dist-info/METADATA
python_library_30153653-1.5.0.dist-info/WHEEL
python_library_30153653-1.5.0.dist-info/top_level.txt
python_library_30153653-1.5.0.dist-info/RECORD
